{"metadata":{"_appTitle":"Unity Container","_appFooter":"<span>Copyright &copy; 2008–2019 <strong>Unity Container</strong> project</span>","_appLogoPath":"images/logo.svg","_appFaviconPath":"images/favicon.png"},"items":[{"name":"Composition","items":[{"name":"Resolution","items":[{"name":"Resolution","href":"composition/resolution/resolution/","uid":"Tutorial.Resolution"},{"name":"Type","href":"composition/resolution/type/"}],"topicUid":"Tutorial.Resolution"},{"name":"Build-Up","items":[{"name":"Build Up","href":"composition/buildup/buildup/","uid":"Tutorial.BuildUp"}],"topicUid":"Tutorial.BuildUp"},{"name":"Type Mapping","items":[{"name":"Service To Implementation","href":"composition/mapping/implementation/","uid":"Tutorial.Mapping.Implementation"},{"name":"Generic Mapping","href":"composition/mapping/generic/","uid":"Tutorial.Mapping.Generic"}],"topicUid":"Tutorial.Mapping"},{"name":"Selection","items":[{"name":"Constructor","href":"composition/selection/constructor/","uid":"Tutorial.Selection.Constructor"}],"topicUid":"Tutorial.Resolution.Selection"},{"name":"Generics","items":[{"name":"Metadata","href":"composition/generics/metadata/","uid":"Tutorial.Generics.Metadata"},{"name":"Lazy","href":"composition/generics/lazy/","uid":"Tutorial.Lazy"},{"name":"Deferred","href":"composition/generics/deferred/","uid":"Tutorial.Deferred"}],"topicUid":"Tutorial.Generics"},{"name":"Collections","href":"composition/collections/"},{"name":"Overrides","items":[{"name":"Parameter","href":"composition/overrides/parameter/","uid":"Tutorial.Resolution.Override.Parameter"},{"name":"Field","href":"composition/overrides/field/","uid":"Tutorial.Resolution.Override.Field"},{"name":"Property","href":"composition/overrides/property/","uid":"Tutorial.Resolution.Override.Property"},{"name":"Dependency","href":"composition/overrides/dependency/","uid":"Tutorial.Resolution.Override.Dependency"}],"topicUid":"Tutorial.Resolution.Override"}],"topicUid":"Tutorial.Composition"},{"name":"Attributed Injection Model","items":[{"name":"Constructor","href":"annotation/constructor/","uid":"Tutorial.Annotation.Constructor"},{"name":"Parameter","href":"annotation/parameter/","uid":"Tutorial.Annotation.Parameter"},{"name":"Method","href":"annotation/method/","uid":"Tutorial.Annotation.Method"},{"name":"Field","href":"annotation/field/","uid":"Tutorial.Annotation.Field"},{"name":"Property","href":"annotation/property/","uid":"Tutorial.Annotation.Property"}],"topicUid":"Tutorial.Annotation"},{"name":"Registration","items":[{"name":"Metadata","href":"registration/metadata/","uid":"Tutorial.Registration.Metadata"},{"name":"Instance Registration","href":"registration/instance/","uid":"Tutorial.Registration.Instance"},{"name":"Factory Registration","href":"registration/factory/","uid":"Tutorial.Registration.Factory"},{"name":"Type Registration","items":[{"name":"Constructor","items":[{"name":"Automatic Selection","href":"registration/type/constructor/automatic/","uid":"Tutorial.Injection.Constructor.Implicit"},{"name":"Attribute Annotation","href":"registration/type/constructor/annotation/","uid":"Tutorial.Injection.Constructor.Annotation"},{"name":"Invoking default ctor()","href":"registration/type/constructor/param_none/","uid":"Tutorial.Injection.Constructor.Default"},{"name":"Select By Parameters Count","href":"registration/type/constructor/param_count/","uid":"Tutorial.Injection.Constructor.Count"},{"name":"Select By Parameter Types","href":"registration/type/constructor/param_types/","uid":"Tutorial.Injection.Constructor.Types"}],"topicUid":"Tutorial.Injection.Constructor"},{"name":"Fields","href":"registration/type/field/","uid":"Tutorial.Injection.Field"},{"name":"Properties","href":"registration/type/property/","uid":"Tutorial.Injection.Property"},{"name":"Method Invocation","href":"registration/type/method/","uid":"Tutorial.Injection.Method"},{"name":"Dependency Injection","items":[{"name":"Resolved values","href":"registration/type/injection/resolved/","uid":"Tutorial.Injection.Resolved"},{"name":"Injected values","href":"registration/type/injection/injected/","uid":"Tutorial.Injection.Injected"},{"name":"Default values","href":"registration/type/injection/default/","uid":"Tutorial.Injection.Default"}],"topicUid":"Tutorial.Injection"}],"topicUid":"Tutorial.Registration.Type"}],"topicUid":"Tutorial.Registration"},{"name":"Hierarchies","href":"hierarchies/","uid":"Tutorial.Container.Hierarchy"},{"name":"Lifetime","items":[{"name":"Transient","href":"lifetime/transient/","uid":"Tutorial.Lifetime.Transient"},{"name":"Singleton","href":"lifetime/singleton/","uid":"Tutorial.Lifetime.Singleton"},{"name":"Container","href":"lifetime/container/","uid":"Tutorial.Lifetime.Container"},{"name":"Container Transient","href":"lifetime/container_transient/","uid":"Tutorial.Lifetime.Container.Transient"},{"name":"Hierarchical","href":"lifetime/hierarchical/","uid":"Tutorial.Lifetime.Hierarchical"},{"name":"Per Resolve","href":"lifetime/resolve/","uid":"Tutorial.Lifetime.Resolve"},{"name":"Per Thread","href":"lifetime/thread/","uid":"Tutorial.Lifetime.Thread"},{"name":"External","href":"lifetime/external/","uid":"Tutorial.Lifetime.External"}],"topicUid":"Tutorial.Lifetime"},{"name":"Extensions","items":[{"name":"Diagnostic","href":"extensions/diagnostic/","uid":"Tutorial.Extension.Diagnostic"},{"name":"Legacy","href":"extensions/legacy/","uid":"Tutorial.Extension.Legacy"},{"name":"Force Activation","href":"extensions/activation/","uid":"Tutorial.Extension.Activation"},{"name":"Force Compilation","href":"extensions/compilation/","uid":"Tutorial.Extension.Compilation"}],"topicUid":"Tutorial.Extensions"}]}